odoo/addons/l10n_th_sequence_range_end/README.rst
odoo/addons/l10n_th_sequence_range_end/__init__.py
odoo/addons/l10n_th_sequence_range_end/__manifest__.py
odoo/addons/l10n_th_sequence_range_end/i18n/l10n_th_sequence_range_end.pot
odoo/addons/l10n_th_sequence_range_end/models/__init__.py
odoo/addons/l10n_th_sequence_range_end/models/ir_sequence.py
odoo/addons/l10n_th_sequence_range_end/models/ir_sequence_date_range.py
odoo/addons/l10n_th_sequence_range_end/readme/CONTRIBUTORS.rst
odoo/addons/l10n_th_sequence_range_end/readme/DESCRIPTION.rst
odoo/addons/l10n_th_sequence_range_end/readme/HISTORY.rst
odoo/addons/l10n_th_sequence_range_end/static/description/icon.png
odoo/addons/l10n_th_sequence_range_end/static/description/index.html
odoo/addons/l10n_th_sequence_range_end/tests/__init__.py
odoo/addons/l10n_th_sequence_range_end/tests/test_ir_sequence_range_end.py
odoo14_addon_l10n_th_sequence_range_end-14.0.1.0.1.dev4.dist-info/METADATA
odoo14_addon_l10n_th_sequence_range_end-14.0.1.0.1.dev4.dist-info/WHEEL
odoo14_addon_l10n_th_sequence_range_end-14.0.1.0.1.dev4.dist-info/top_level.txt
odoo14_addon_l10n_th_sequence_range_end-14.0.1.0.1.dev4.dist-info/RECORD
